ou_Axion_limit
